Workbook

Sheet Dashboard
A1: Personal Financial Model — Executive Dashboard
A3: Model purpose | B3: Centralize income, spending, bills, debt, cash, investments, and financial goals.
A4: Update cadence | B4: Monthly; transaction-level data can be imported more frequently.
A5: Bank connection | B5: Designed for future CSV/API aggregation; never store bank passwords in this workbook.
A7: Key Monthly Metrics
A8: Monthly Net Income | B8: =SUMIFS(Transactions!$H:$H,Transactions!$D:$D,"Income")
A9: Monthly Spending | B9: =-SUMIFS(Transactions!$H:$H,Transactions!$D:$D,"Expense")
A10: Monthly Surplus / (Deficit) | B10: =B8-B9
A11: Savings Rate | B11: =IFERROR(B10/B8,0)
A14: Balance Sheet Snapshot
A15: Cash | B15: =SUMIFS(Accounts!$E:$E,Accounts!$C:$C,"Cash")
A16: Investments | B16: =SUMIFS(Accounts!$E:$E,Accounts!$C:$C,"Investment")
A17: Debt | B17: =SUM(Debt!$E:$E)
A18: Net Worth | B18: =B15+B16-B17
A21: Goal Progress
A22: Goal | B22: Progress | C22: Remaining ($)
A23: ='Goals'!A4 | B23: =IFERROR('Goals'!C4/'Goals'!B4,0) | C23: ='Goals'!B4-'Goals'!C4
A24: ='Goals'!A5
A25: ='Goals'!A6 | B25: =IFERROR('Goals'!C6/'Goals'!B6,0) | C25: ='Goals'!B6-'Goals'!C6
A28: Automation / Data Quality
A29: Raw Rows Imported | B29: =COUNTA('Raw Import'!A:A)-1
A30: Normalized Transactions | B30: =COUNTA(Transactions!A:A)-1
A31: Uncategorized | B31: =COUNTIF(Transactions!$E:$E,"Uncategorized")
A32: Needs Review | B32: =COUNTIF(Transactions!$L:$L,"Review")
A33: Last Raw Import | B33: =MAX('Raw Import'!L:L)

Sheet Accounts
A1: Accounts & Net Worth
A3: Account ID | B3: Institution | C3: Type | D3: Account Name | E3: Current Balance | F3: As Of Date | G3: Notes

Sheet Transactions
A1: Transactions — Normalized Reporting Ledger
A3: Clean ledger used by the budget and dashboard. Source data comes from Raw Import; category and recurring status are assigned automatically from Category Rules.
A4: Date | B4: Account ID | C4: Merchant / Description | D4: Type | E4: Category | F4: Subcategory | G4: Amount ($) | H4: Signed Amount ($) | I4: Month | J4: Recurring? | K4: Notes | L4: Review Status | M4: Source Transaction ID | N4: Source | O4: Rule Match | P4: Fingerprint
N5: =IF('Raw Import'!K5="","",'Raw Import'!K5) | O5: =IF(C5="","",IF(AND('Category Rules'!$B$4="Yes",C5<>"",ISNUMBER(SEARCH('Category Rules'!$E$4,C5))),'Category Rules'!$E$4,IF(AND('Category Rules'!$B$5="Yes",C5<>"",ISNUMBER(SEARCH('Category Rules'!$E$5,C5))),'Category Rules'!$E$5,IF(AND('Category Rules'!$B$6="Yes",C5<>"",ISNUMBER(SEARCH('Category Rules'!$E$6,C5))),'Category Rules'!$E$6,IF(AND('Category Rules'!$B$7="Yes",C5<>"",ISNUMBER(SEARCH('Category Rules'!$E$7,C5))),'Category Rules'!$E$7,IF(AND('Category Rules'!$B$8="Yes",C5<>"",ISNUMBER(SEARCH('Category Rules'!$E$8,C5))),'Category Rules'!$E$8,IF(AND('Category Rules'!$B$9="Yes",C5<>"",ISNUMBER(SEARCH('Category Rules'!$E$9,C5))),'Category Rules'!$E$9,IF(AND('Category Rules'!$B$10="Yes",C5<>"",ISNUMBER(SEARCH('Category Rules'!$E$10,C5))),'Category Rules'!$E$10,IF(AND('Category Rules'!$B$11="Yes",C5<>"",ISNUMBER(SEARCH('Category Rules'!$E$11,C5))),'Category Rules'!$E$11,IF(AND('Category Rules'!$B$12="Yes",C5<>"",ISNUMBER(SEARCH('Category Rules'!$E$12,C5))),'Category Rules'!$E$12,IF(AND('Category Rules'!$B$13="Yes",C5<>"",ISNUMBER(SEARCH('Category Rules'!$E$13,C5))),'Category Rules'!$E$13,IF(AND('Category Rules'!$B$14="Yes",C5<>"",ISNUMBER(SEARCH('Category Rules'!$E$14,C5))),'Category Rules'!$E$14,IF(AND('Category Rules'!$B$15="Yes",C5<>"",ISNUMBER(SEARCH('Category Rules'!$E$15,C5))),'Category Rules'!$E$15,IF(AND('Category Rules'!$B$16="Yes",C5<>"",ISNUMBER(SEARCH('Category Rules'!$E$16,C5))),'Category Rules'!$E$16,IF(AND('Category Rules'!$B$17="Yes",C5<>"",ISNUMBER(SEARCH('Category Rules'!$E$17,C5))),'Category Rules'!$E$17,IF(AND('Category Rules'!$B$18="Yes",C5<>"",ISNUMBER(SEARCH('Category Rules'!$E$18,C5))),'Category Rules'!$E$18,IF(AND('Category Rules'!$B$19="Yes",C5<>"",ISNUMBER(SEARCH('Category Rules'!$E$19,C5))),'Category Rules'!$E$19,"No rule matched"))))))))))))))))) | P5: =IF(OR(A5="",B5="",C5="",H5=""),"",TEXT(A5,"yyyymmdd")&"|"&B5&"|"&C5&"|"&TEXT(H5,"0.00"))
N6: =IF('Raw Import'!K6="","",'Raw Import'!K6) | O6: =IF(C6="","",IF(AND('Category Rules'!$B$4="Yes",C6<>"",ISNUMBER(SEARCH('Category Rules'!$E$4,C6))),'Category Rules'!$E$4,IF(AND('Category Rules'!$B$5="Yes",C6<>"",ISNUMBER(SEARCH('Category Rules'!$E$5,C6))),'Category Rules'!$E$5,IF(AND('Category Rules'!$B$6="Yes",C6<>"",ISNUMBER(SEARCH('Category Rules'!$E$6,C6))),'Category Rules'!$E$6,IF(AND('Category Rules'!$B$7="Yes",C6<>"",ISNUMBER(SEARCH('Category Rules'!$E$7,C6))),'Category Rules'!$E$7,IF(AND('Category Rules'!$B$8="Yes",C6<>"",ISNUMBER(SEARCH('Category Rules'!$E$8,C6))),'Category Rules'!$E$8,IF(AND('Category Rules'!$B$9="Yes",C6<>"",ISNUMBER(SEARCH('Category Rules'!$E$9,C6))),'Category Rules'!$E$9,IF(AND('Category Rules'!$B$10="Yes",C6<>"",ISNUMBER(SEARCH('Category Rules'!$E$10,C6))),'Category Rules'!$E$10,IF(AND('Category Rules'!$B$11="Yes",C6<>"",ISNUMBER(SEARCH('Category Rules'!$E$11,C6))),'Category Rules'!$E$11,IF(AND('Category Rules'!$B$12="Yes",C6<>"",ISNUMBER(SEARCH('Category Rules'!$E$12,C6))),'Category Rules'!$E$12,IF(AND('Category Rules'!$B$13="Yes",C6<>"",ISNUMBER(SEARCH('Category Rules'!$E$13,C6))),'Category Rules'!$E$13,IF(AND('Category Rules'!$B$14="Yes",C6<>"",ISNUMBER(SEARCH('Category Rules'!$E$14,C6))),'Category Rules'!$E$14,IF(AND('Category Rules'!$B$15="Yes",C6<>"",ISNUMBER(SEARCH('Category Rules'!$E$15,C6))),'Category Rules'!$E$15,IF(AND('Category Rules'!$B$16="Yes",C6<>"",ISNUMBER(SEARCH('Category Rules'!$E$16,C6))),'Category Rules'!$E$16,IF(AND('Category Rules'!$B$17="Yes",C6<>"",ISNUMBER(SEARCH('Category Rules'!$E$17,C6))),'Category Rules'!$E$17,IF(AND('Category Rules'!$B$18="Yes",C6<>"",ISNUMBER(SEARCH('Category Rules'!$E$18,C6))),'Category Rules'!$E$18,IF(AND('Category Rules'!$B$19="Yes",C6<>"",ISNUMBER(SEARCH('Category Rules'!$E$19,C6))),'Category Rules'!$E$19,"No rule matched"))))))))))))))))) | P6: =IF(OR(A6="",B6="",C6="",H6=""),"",TEXT(A6,"yyyymmdd")&"|"&B6&"|"&C6&"|"&TEXT(H6,"0.00"))
N7: =IF('Raw Import'!K7="","",'Raw Import'!K7) | O7: =IF(C7="","",IF(AND('Category Rules'!$B$4="Yes",C7<>"",ISNUMBER(SEARCH('Category Rules'!$E$4,C7))),'Category Rules'!$E$4,IF(AND('Category Rules'!$B$5="Yes",C7<>"",ISNUMBER(SEARCH('Category Rules'!$E$5,C7))),'Category Rules'!$E$5,IF(AND('Category Rules'!$B$6="Yes",C7<>"",ISNUMBER(SEARCH('Category Rules'!$E$6,C7))),'Category Rules'!$E$6,IF(AND('Category Rules'!$B$7="Yes",C7<>"",ISNUMBER(SEARCH('Category Rules'!$E$7,C7))),'Category Rules'!$E$7,IF(AND('Category Rules'!$B$8="Yes",C7<>"",ISNUMBER(SEARCH('Category Rules'!$E$8,C7))),'Category Rules'!$E$8,IF(AND('Category Rules'!$B$9="Yes",C7<>"",ISNUMBER(SEARCH('Category Rules'!$E$9,C7))),'Category Rules'!$E$9,IF(AND('Category Rules'!$B$10="Yes",C7<>"",ISNUMBER(SEARCH('Category Rules'!$E$10,C7))),'Category Rules'!$E$10,IF(AND('Category Rules'!$B$11="Yes",C7<>"",ISNUMBER(SEARCH('Category Rules'!$E$11,C7))),'Category Rules'!$E$11,IF(AND('Category Rules'!$B$12="Yes",C7<>"",ISNUMBER(SEARCH('Category Rules'!$E$12,C7))),'Category Rules'!$E$12,IF(AND('Category Rules'!$B$13="Yes",C7<>"",ISNUMBER(SEARCH('Category Rules'!$E$13,C7))),'Category Rules'!$E$13,IF(AND('Category Rules'!$B$14="Yes",C7<>"",ISNUMBER(SEARCH('Category Rules'!$E$14,C7))),'Category Rules'!$E$14,IF(AND('Category Rules'!$B$15="Yes",C7<>"",ISNUMBER(SEARCH('Category Rules'!$E$15,C7))),'Category Rules'!$E$15,IF(AND('Category Rules'!$B$16="Yes",C7<>"",ISNUMBER(SEARCH('Category Rules'!$E$16,C7))),'Category Rules'!$E$16,IF(AND('Category Rules'!$B$17="Yes",C7<>"",ISNUMBER(SEARCH('Category Rules'!$E$17,C7))),'Category Rules'!$E$17,IF(AND('Category Rules'!$B$18="Yes",C7<>"",ISNUMBER(SEARCH('Category Rules'!$E$18,C7))),'Category Rules'!$E$18,IF(AND('Category Rules'!$B$19="Yes",C7<>"",ISNUMBER(SEARCH('Category Rules'!$E$19,C7))),'Category Rules'!$E$19,"No rule matched"))))))))))))))))) | P7: =IF(OR(A7="",B7="",C7="",H7=""),"",TEXT(A7,"yyyymmdd")&"|"&B7&"|"&C7&"|"&TEXT(H7,"0.00"))
N8: =IF('Raw Import'!K8="","",'Raw Import'!K8) | O8: =IF(C8="","",IF(AND('Category Rules'!$B$4="Yes",C8<>"",ISNUMBER(SEARCH('Category Rules'!$E$4,C8))),'Category Rules'!$E$4,IF(AND('Category Rules'!$B$5="Yes",C8<>"",ISNUMBER(SEARCH('Category Rules'!$E$5,C8))),'Category Rules'!$E$5,IF(AND('Category Rules'!$B$6="Yes",C8<>"",ISNUMBER(SEARCH('Category Rules'!$E$6,C8))),'Category Rules'!$E$6,IF(AND('Category Rules'!$B$7="Yes",C8<>"",ISNUMBER(SEARCH('Category Rules'!$E$7,C8))),'Category Rules'!$E$7,IF(AND('Category Rules'!$B$8="Yes",C8<>"",ISNUMBER(SEARCH('Category Rules'!$E$8,C8))),'Category Rules'!$E$8,IF(AND('Category Rules'!$B$9="Yes",C8<>"",ISNUMBER(SEARCH('Category Rules'!$E$9,C8))),'Category Rules'!$E$9,IF(AND('Category Rules'!$B$10="Yes",C8<>"",ISNUMBER(SEARCH('Category Rules'!$E$10,C8))),'Category Rules'!$E$10,IF(AND('Category Rules'!$B$11="Yes",C8<>"",ISNUMBER(SEARCH('Category Rules'!$E$11,C8))),'Category Rules'!$E$11,IF(AND('Category Rules'!$B$12="Yes",C8<>"",ISNUMBER(SEARCH('Category Rules'!$E$12,C8))),'Category Rules'!$E$12,IF(AND('Category Rules'!$B$13="Yes",C8<>"",ISNUMBER(SEARCH('Category Rules'!$E$13,C8))),'Category Rules'!$E$13,IF(AND('Category Rules'!$B$14="Yes",C8<>"",ISNUMBER(SEARCH('Category Rules'!$E$14,C8))),'Category Rules'!$E$14,IF(AND('Category Rules'!$B$15="Yes",C8<>"",ISNUMBER(SEARCH('Category Rules'!$E$15,C8))),'Category Rules'!$E$15,IF(AND('Category Rules'!$B$16="Yes",C8<>"",ISNUMBER(SEARCH('Category Rules'!$E$16,C8))),'Category Rules'!$E$16,IF(AND('Category Rules'!$B$17="Yes",C8<>"",ISNUMBER(SEARCH('Category Rules'!$E$17,C8))),'Category Rules'!$E$17,IF(AND('Category Rules'!$B$18="Yes",C8<>"",ISNUMBER(SEARCH('Category Rules'!$E$18,C8))),'Category Rules'!$E$18,IF(AND('Category Rules'!$B$19="Yes",C8<>"",ISNUMBER(SEARCH('Category Rules'!$E$19,C8))),'Category Rules'!$E$19,"No rule matched"))))))))))))))))) | P8: =IF(OR(A8="",B8="",C8="",H8=""),"",TEXT(A8,"yyyymmdd")&"|"&B8&"|"&C8&"|"&TEXT(H8,"0.00"))
N9: =IF('Raw Import'!K9="","",'Raw Import'!K9) | O9: =IF(C9="","",IF(AND('Category Rules'!$B$4="Yes",C9<>"",ISNUMBER(SEARCH('Category Rules'!$E$4,C9))),'Category Rules'!$E$4,IF(AND('Category Rules'!$B$5="Yes",C9<>"",ISNUMBER(SEARCH('Category Rules'!$E$5,C9))),'Category Rules'!$E$5,IF(AND('Category Rules'!$B$6="Yes",C9<>"",ISNUMBER(SEARCH('Category Rules'!$E$6,C9))),'Category Rules'!$E$6,IF(AND('Category Rules'!$B$7="Yes",C9<>"",ISNUMBER(SEARCH('Category Rules'!$E$7,C9))),'Category Rules'!$E$7,IF(AND('Category Rules'!$B$8="Yes",C9<>"",ISNUMBER(SEARCH('Category Rules'!$E$8,C9))),'Category Rules'!$E$8,IF(AND('Category Rules'!$B$9="Yes",C9<>"",ISNUMBER(SEARCH('Category Rules'!$E$9,C9))),'Category Rules'!$E$9,IF(AND('Category Rules'!$B$10="Yes",C9<>"",ISNUMBER(SEARCH('Category Rules'!$E$10,C9))),'Category Rules'!$E$10,IF(AND('Category Rules'!$B$11="Yes",C9<>"",ISNUMBER(SEARCH('Category Rules'!$E$11,C9))),'Category Rules'!$E$11,IF(AND('Category Rules'!$B$12="Yes",C9<>"",ISNUMBER(SEARCH('Category Rules'!$E$12,C9))),'Category Rules'!$E$12,IF(AND('Category Rules'!$B$13="Yes",C9<>"",ISNUMBER(SEARCH('Category Rules'!$E$13,C9))),'Category Rules'!$E$13,IF(AND('Category Rules'!$B$14="Yes",C9<>"",ISNUMBER(SEARCH('Category Rules'!$E$14,C9))),'Category Rules'!$E$14,IF(AND('Category Rules'!$B$15="Yes",C9<>"",ISNUMBER(SEARCH('Category Rules'!$E$15,C9))),'Category Rules'!$E$15,IF(AND('Category Rules'!$B$16="Yes",C9<>"",ISNUMBER(SEARCH('Category Rules'!$E$16,C9))),'Category Rules'!$E$16,IF(AND('Category Rules'!$B$17="Yes",C9<>"",ISNUMBER(SEARCH('Category Rules'!$E$17,C9))),'Category Rules'!$E$17,IF(AND('Category Rules'!$B$18="Yes",C9<>"",ISNUMBER(SEARCH('Category Rules'!$E$18,C9))),'Category Rules'!$E$18,IF(AND('Category Rules'!$B$19="Yes",C9<>"",ISNUMBER(SEARCH('Category Rules'!$E$19,C9))),'Category Rules'!$E$19,"No rule matched"))))))))))))))))) | P9: =IF(OR(A9="",B9="",C9="",H9=""),"",TEXT(A9,"yyyymmdd")&"|"&B9&"|"&C9&"|"&TEXT(H9,"0.00"))
N10: =IF('Raw Import'!K10="","",'Raw Import'!K10) | O10: =IF(C10="","",IF(AND('Category Rules'!$B$4="Yes",C10<>"",ISNUMBER(SEARCH('Category Rules'!$E$4,C10))),'Category Rules'!$E$4,IF(AND('Category Rules'!$B$5="Yes",C10<>"",ISNUMBER(SEARCH('Category Rules'!$E$5,C10))),'Category Rules'!$E$5,IF(AND('Category Rules'!$B$6="Yes",C10<>"",ISNUMBER(SEARCH('Category Rules'!$E$6,C10))),'Category Rules'!$E$6,IF(AND('Category Rules'!$B$7="Yes",C10<>"",ISNUMBER(SEARCH('Category Rules'!$E$7,C10))),'Category Rules'!$E$7,IF(AND('Category Rules'!$B$8="Yes",C10<>"",ISNUMBER(SEARCH('Category Rules'!$E$8,C10))),'Category Rules'!$E$8,IF(AND('Category Rules'!$B$9="Yes",C10<>"",ISNUMBER(SEARCH('Category Rules'!$E$9,C10))),'Category Rules'!$E$9,IF(AND('Category Rules'!$B$10="Yes",C10<>"",ISNUMBER(SEARCH('Category Rules'!$E$10,C10))),'Category Rules'!$E$10,IF(AND('Category Rules'!$B$11="Yes",C10<>"",ISNUMBER(SEARCH('Category Rules'!$E$11,C10))),'Category Rules'!$E$11,IF(AND('Category Rules'!$B$12="Yes",C10<>"",ISNUMBER(SEARCH('Category Rules'!$E$12,C10))),'Category Rules'!$E$12,IF(AND('Category Rules'!$B$13="Yes",C10<>"",ISNUMBER(SEARCH('Category Rules'!$E$13,C10))),'Category Rules'!$E$13,IF(AND('Category Rules'!$B$14="Yes",C10<>"",ISNUMBER(SEARCH('Category Rules'!$E$14,C10))),'Category Rules'!$E$14,IF(AND('Category Rules'!$B$15="Yes",C10<>"",ISNUMBER(SEARCH('Category Rules'!$E$15,C10))),'Category Rules'!$E$15,IF(AND('Category Rules'!$B$16="Yes",C10<>"",ISNUMBER(SEARCH('Category Rules'!$E$16,C10))),'Category Rules'!$E$16,IF(AND('Category Rules'!$B$17="Yes",C10<>"",ISNUMBER(SEARCH('Category Rules'!$E$17,C10))),'Category Rules'!$E$17,IF(AND('Category Rules'!$B$18="Yes",C10<>"",ISNUMBER(SEARCH('Category Rules'!$E$18,C10))),'Category Rules'!$E$18,IF(AND('Category Rules'!$B$19="Yes",C10<>"",ISNUMBER(SEARCH('Category Rules'!$E$19,C10))),'Category Rules'!$E$19,"No rule matched"))))))))))))))))) | P10: =IF(OR(A10="",B10="",C10="",H10=""),"",TEXT(A10,"yyyymmdd")&"|"&B10&"|"&C10&"|"&TEXT(H10,"0.00"))
N11: =IF('Raw Import'!K11="","",'Raw Import'!K11) | O11: =IF(C11="","",IF(AND('Category Rules'!$B$4="Yes",C11<>"",ISNUMBER(SEARCH('Category Rules'!$E$4,C11))),'Category Rules'!$E$4,IF(AND('Category Rules'!$B$5="Yes",C11<>"",ISNUMBER(SEARCH('Category Rules'!$E$5,C11))),'Category Rules'!$E$5,IF(AND('Category Rules'!$B$6="Yes",C11<>"",ISNUMBER(SEARCH('Category Rules'!$E$6,C11))),'Category Rules'!$E$6,IF(AND('Category Rules'!$B$7="Yes",C11<>"",ISNUMBER(SEARCH('Category Rules'!$E$7,C11))),'Category Rules'!$E$7,IF(AND('Category Rules'!$B$8="Yes",C11<>"",ISNUMBER(SEARCH('Category Rules'!$E$8,C11))),'Category Rules'!$E$8,IF(AND('Category Rules'!$B$9="Yes",C11<>"",ISNUMBER(SEARCH('Category Rules'!$E$9,C11))),'Category Rules'!$E$9,IF(AND('Category Rules'!$B$10="Yes",C11<>"",ISNUMBER(SEARCH('Category Rules'!$E$10,C11))),'Category Rules'!$E$10,IF(AND('Category Rules'!$B$11="Yes",C11<>"",ISNUMBER(SEARCH('Category Rules'!$E$11,C11))),'Category Rules'!$E$11,IF(AND('Category Rules'!$B$12="Yes",C11<>"",ISNUMBER(SEARCH('Category Rules'!$E$12,C11))),'Category Rules'!$E$12,IF(AND('Category Rules'!$B$13="Yes",C11<>"",ISNUMBER(SEARCH('Category Rules'!$E$13,C11))),'Category Rules'!$E$13,IF(AND('Category Rules'!$B$14="Yes",C11<>"",ISNUMBER(SEARCH('Category Rules'!$E$14,C11))),'Category Rules'!$E$14,IF(AND('Category Rules'!$B$15="Yes",C11<>"",ISNUMBER(SEARCH('Category Rules'!$E$15,C11))),'Category Rules'!$E$15,IF(AND('Category Rules'!$B$16="Yes",C11<>"",ISNUMBER(SEARCH('Category Rules'!$E$16,C11))),'Category Rules'!$E$16,IF(AND('Category Rules'!$B$17="Yes",C11<>"",ISNUMBER(SEARCH('Category Rules'!$E$17,C11))),'Category Rules'!$E$17,IF(AND('Category Rules'!$B$18="Yes",C11<>"",ISNUMBER(SEARCH('Category Rules'!$E$18,C11))),'Category Rules'!$E$18,IF(AND('Category Rules'!$B$19="Yes",C11<>"",ISNUMBER(SEARCH('Category Rules'!$E$19,C11))),'Category Rules'!$E$19,"No rule matched"))))))))))))))))) | P11: =IF(OR(A11="",B11="",C11="",H11=""),"",TEXT(A11,"yyyymmdd")&"|"&B11&"|"&C11&"|"&TEXT(H11,"0.00"))
N12: =IF('Raw Import'!K12="","",'Raw Import'!K12) | O12: =IF(C12="","",IF(AND('Category Rules'!$B$4="Yes",C12<>"",ISNUMBER(SEARCH('Category Rules'!$E$4,C12))),'Category Rules'!$E$4,IF(AND('Category Rules'!$B$5="Yes",C12<>"",ISNUMBER(SEARCH('Category Rules'!$E$5,C12))),'Category Rules'!$E$5,IF(AND('Category Rules'!$B$6="Yes",C12<>"",ISNUMBER(SEARCH('Category Rules'!$E$6,C12))),'Category Rules'!$E$6,IF(AND('Category Rules'!$B$7="Yes",C12<>"",ISNUMBER(SEARCH('Category Rules'!$E$7,C12))),'Category Rules'!$E$7,IF(AND('Category Rules'!$B$8="Yes",C12<>"",ISNUMBER(SEARCH('Category Rules'!$E$8,C12))),'Category Rules'!$E$8,IF(AND('Category Rules'!$B$9="Yes",C12<>"",ISNUMBER(SEARCH('Category Rules'!$E$9,C12))),'Category Rules'!$E$9,IF(AND('Category Rules'!$B$10="Yes",C12<>"",ISNUMBER(SEARCH('Category Rules'!$E$10,C12))),'Category Rules'!$E$10,IF(AND('Category Rules'!$B$11="Yes",C12<>"",ISNUMBER(SEARCH('Category Rules'!$E$11,C12))),'Category Rules'!$E$11,IF(AND('Category Rules'!$B$12="Yes",C12<>"",ISNUMBER(SEARCH('Category Rules'!$E$12,C12))),'Category Rules'!$E$12,IF(AND('Category Rules'!$B$13="Yes",C12<>"",ISNUMBER(SEARCH('Category Rules'!$E$13,C12))),'Category Rules'!$E$13,IF(AND('Category Rules'!$B$14="Yes",C12<>"",ISNUMBER(SEARCH('Category Rules'!$E$14,C12))),'Category Rules'!$E$14,IF(AND('Category Rules'!$B$15="Yes",C12<>"",ISNUMBER(SEARCH('Category Rules'!$E$15,C12))),'Category Rules'!$E$15,IF(AND('Category Rules'!$B$16="Yes",C12<>"",ISNUMBER(SEARCH('Category Rules'!$E$16,C12))),'Category Rules'!$E$16,IF(AND('Category Rules'!$B$17="Yes",C12<>"",ISNUMBER(SEARCH('Category Rules'!$E$17,C12))),'Category Rules'!$E$17,IF(AND('Category Rules'!$B$18="Yes",C12<>"",ISNUMBER(SEARCH('Category Rules'!$E$18,C12))),'Category Rules'!$E$18,IF(AND('Category Rules'!$B$19="Yes",C12<>"",ISNUMBER(SEARCH('Category Rules'!$E$19,C12))),'Category Rules'!$E$19,"No rule matched"))))))))))))))))) | P12: =IF(OR(A12="",B12="",C12="",H12=""),"",TEXT(A12,"yyyymmdd")&"|"&B12&"|"&C12&"|"&TEXT(H12,"0.00"))
N13: =IF('Raw Import'!K13="","",'Raw Import'!K13) | O13: =IF(C13="","",IF(AND('Category Rules'!$B$4="Yes",C13<>"",ISNUMBER(SEARCH('Category Rules'!$E$4,C13))),'Category Rules'!$E$4,IF(AND('Category Rules'!$B$5="Yes",C13<>"",ISNUMBER(SEARCH('Category Rules'!$E$5,C13))),'Category Rules'!$E$5,IF(AND('Category Rules'!$B$6="Yes",C13<>"",ISNUMBER(SEARCH('Category Rules'!$E$6,C13))),'Category Rules'!$E$6,IF(AND('Category Rules'!$B$7="Yes",C13<>"",ISNUMBER(SEARCH('Category Rules'!$E$7,C13))),'Category Rules'!$E$7,IF(AND('Category Rules'!$B$8="Yes",C13<>"",ISNUMBER(SEARCH('Category Rules'!$E$8,C13))),'Category Rules'!$E$8,IF(AND('Category Rules'!$B$9="Yes",C13<>"",ISNUMBER(SEARCH('Category Rules'!$E$9,C13))),'Category Rules'!$E$9,IF(AND('Category Rules'!$B$10="Yes",C13<>"",ISNUMBER(SEARCH('Category Rules'!$E$10,C13))),'Category Rules'!$E$10,IF(AND('Category Rules'!$B$11="Yes",C13<>"",ISNUMBER(SEARCH('Category Rules'!$E$11,C13))),'Category Rules'!$E$11,IF(AND('Category Rules'!$B$12="Yes",C13<>"",ISNUMBER(SEARCH('Category Rules'!$E$12,C13))),'Category Rules'!$E$12,IF(AND('Category Rules'!$B$13="Yes",C13<>"",ISNUMBER(SEARCH('Category Rules'!$E$13,C13))),'Category Rules'!$E$13,IF(AND('Category Rules'!$B$14="Yes",C13<>"",ISNUMBER(SEARCH('Category Rules'!$E$14,C13))),'Category Rules'!$E$14,IF(AND('Category Rules'!$B$15="Yes",C13<>"",ISNUMBER(SEARCH('Category Rules'!$E$15,C13))),'Category Rules'!$E$15,IF(AND('Category Rules'!$B$16="Yes",C13<>"",ISNUMBER(SEARCH('Category Rules'!$E$16,C13))),'Category Rules'!$E$16,IF(AND('Category Rules'!$B$17="Yes",C13<>"",ISNUMBER(SEARCH('Category Rules'!$E$17,C13))),'Category Rules'!$E$17,IF(AND('Category Rules'!$B$18="Yes",C13<>"",ISNUMBER(SEARCH('Category Rules'!$E$18,C13))),'Category Rules'!$E$18,IF(AND('Category Rules'!$B$19="Yes",C13<>"",ISNUMBER(SEARCH('Category Rules'!$E$19,C13))),'Category Rules'!$E$19,"No rule matched"))))))))))))))))) | P13: =IF(OR(A13="",B13="",C13="",H13=""),"",TEXT(A13,"yyyymmdd")&"|"&B13&"|"&C13&"|"&TEXT(H13,"0.00"))
N14: =IF('Raw Import'!K14="","",'Raw Import'!K14) | O14: =IF(C14="","",IF(AND('Category Rules'!$B$4="Yes",C14<>"",ISNUMBER(SEARCH('Category Rules'!$E$4,C14))),'Category Rules'!$E$4,IF(AND('Category Rules'!$B$5="Yes",C14<>"",ISNUMBER(SEARCH('Category Rules'!$E$5,C14))),'Category Rules'!$E$5,IF(AND('Category Rules'!$B$6="Yes",C14<>"",ISNUMBER(SEARCH('Category Rules'!$E$6,C14))),'Category Rules'!$E$6,IF(AND('Category Rules'!$B$7="Yes",C14<>"",ISNUMBER(SEARCH('Category Rules'!$E$7,C14))),'Category Rules'!$E$7,IF(AND('Category Rules'!$B$8="Yes",C14<>"",ISNUMBER(SEARCH('Category Rules'!$E$8,C14))),'Category Rules'!$E$8,IF(AND('Category Rules'!$B$9="Yes",C14<>"",ISNUMBER(SEARCH('Category Rules'!$E$9,C14))),'Category Rules'!$E$9,IF(AND('Category Rules'!$B$10="Yes",C14<>"",ISNUMBER(SEARCH('Category Rules'!$E$10,C14))),'Category Rules'!$E$10,IF(AND('Category Rules'!$B$11="Yes",C14<>"",ISNUMBER(SEARCH('Category Rules'!$E$11,C14))),'Category Rules'!$E$11,IF(AND('Category Rules'!$B$12="Yes",C14<>"",ISNUMBER(SEARCH('Category Rules'!$E$12,C14))),'Category Rules'!$E$12,IF(AND('Category Rules'!$B$13="Yes",C14<>"",ISNUMBER(SEARCH('Category Rules'!$E$13,C14))),'Category Rules'!$E$13,IF(AND('Category Rules'!$B$14="Yes",C14<>"",ISNUMBER(SEARCH('Category Rules'!$E$14,C14))),'Category Rules'!$E$14,IF(AND('Category Rules'!$B$15="Yes",C14<>"",ISNUMBER(SEARCH('Category Rules'!$E$15,C14))),'Category Rules'!$E$15,IF(AND('Category Rules'!$B$16="Yes",C14<>"",ISNUMBER(SEARCH('Category Rules'!$E$16,C14))),'Category Rules'!$E$16,IF(AND('Category Rules'!$B$17="Yes",C14<>"",ISNUMBER(SEARCH('Category Rules'!$E$17,C14))),'Category Rules'!$E$17,IF(AND('Category Rules'!$B$18="Yes",C14<>"",ISNUMBER(SEARCH('Category Rules'!$E$18,C14))),'Category Rules'!$E$18,IF(AND('Category Rules'!$B$19="Yes",C14<>"",ISNUMBER(SEARCH('Category Rules'!$E$19,C14))),'Category Rules'!$E$19,"No rule matched"))))))))))))))))) | P14: =IF(OR(A14="",B14="",C14="",H14=""),"",TEXT(A14,"yyyymmdd")&"|"&B14&"|"&C14&"|"&TEXT(H14,"0.00"))
N15: =IF('Raw Import'!K15="","",'Raw Import'!K15) | O15: =IF(C15="","",IF(AND('Category Rules'!$B$4="Yes",C15<>"",ISNUMBER(SEARCH('Category Rules'!$E$4,C15))),'Category Rules'!$E$4,IF(AND('Category Rules'!$B$5="Yes",C15<>"",ISNUMBER(SEARCH('Category Rules'!$E$5,C15))),'Category Rules'!$E$5,IF(AND('Category Rules'!$B$6="Yes",C15<>"",ISNUMBER(SEARCH('Category Rules'!$E$6,C15))),'Category Rules'!$E$6,IF(AND('Category Rules'!$B$7="Yes",C15<>"",ISNUMBER(SEARCH('Category Rules'!$E$7,C15))),'Category Rules'!$E$7,IF(AND('Category Rules'!$B$8="Yes",C15<>"",ISNUMBER(SEARCH('Category Rules'!$E$8,C15))),'Category Rules'!$E$8,IF(AND('Category Rules'!$B$9="Yes",C15<>"",ISNUMBER(SEARCH('Category Rules'!$E$9,C15))),'Category Rules'!$E$9,IF(AND('Category Rules'!$B$10="Yes",C15<>"",ISNUMBER(SEARCH('Category Rules'!$E$10,C15))),'Category Rules'!$E$10,IF(AND('Category Rules'!$B$11="Yes",C15<>"",ISNUMBER(SEARCH('Category Rules'!$E$11,C15))),'Category Rules'!$E$11,IF(AND('Category Rules'!$B$12="Yes",C15<>"",ISNUMBER(SEARCH('Category Rules'!$E$12,C15))),'Category Rules'!$E$12,IF(AND('Category Rules'!$B$13="Yes",C15<>"",ISNUMBER(SEARCH('Category Rules'!$E$13,C15))),'Category Rules'!$E$13,IF(AND('Category Rules'!$B$14="Yes",C15<>"",ISNUMBER(SEARCH('Category Rules'!$E$14,C15))),'Category Rules'!$E$14,IF(AND('Category Rules'!$B$15="Yes",C15<>"",ISNUMBER(SEARCH('Category Rules'!$E$15,C15))),'Category Rules'!$E$15,IF(AND('Category Rules'!$B$16="Yes",C15<>"",ISNUMBER(SEARCH('Category Rules'!$E$16,C15))),'Category Rules'!$E$16,IF(AND('Category Rules'!$B$17="Yes",C15<>"",ISNUMBER(SEARCH('Category Rules'!$E$17,C15))),'Category Rules'!$E$17,IF(AND('Category Rules'!$B$18="Yes",C15<>"",ISNUMBER(SEARCH('Category Rules'!$E$18,C15))),'Category Rules'!$E$18,IF(AND('Category Rules'!$B$19="Yes",C15<>"",ISNUMBER(SEARCH('Category Rules'!$E$19,C15))),'Category Rules'!$E$19,"No rule matched"))))))))))))))))) | P15: =IF(OR(A15="",B15="",C15="",H15=""),"",TEXT(A15,"yyyymmdd")&"|"&B15&"|"&C15&"|"&TEXT(H15,"0.00"))
N16: =IF('Raw Import'!K16="","",'Raw Import'!K16) | O16: =IF(C16="","",IF(AND('Category Rules'!$B$4="Yes",C16<>"",ISNUMBER(SEARCH('Category Rules'!$E$4,C16))),'Category Rules'!$E$4,IF(AND('Category Rules'!$B$5="Yes",C16<>"",ISNUMBER(SEARCH('Category Rules'!$E$5,C16))),'Category Rules'!$E$5,IF(AND('Category Rules'!$B$6="Yes",C16<>"",ISNUMBER(SEARCH('Category Rules'!$E$6,C16))),'Category Rules'!$E$6,IF(AND('Category Rules'!$B$7="Yes",C16<>"",ISNUMBER(SEARCH('Category Rules'!$E$7,C16))),'Category Rules'!$E$7,IF(AND('Category Rules'!$B$8="Yes",C16<>"",ISNUMBER(SEARCH('Category Rules'!$E$8,C16))),'Category Rules'!$E$8,IF(AND('Category Rules'!$B$9="Yes",C16<>"",ISNUMBER(SEARCH('Category Rules'!$E$9,C16))),'Category Rules'!$E$9,IF(AND('Category Rules'!$B$10="Yes",C16<>"",ISNUMBER(SEARCH('Category Rules'!$E$10,C16))),'Category Rules'!$E$10,IF(AND('Category Rules'!$B$11="Yes",C16<>"",ISNUMBER(SEARCH('Category Rules'!$E$11,C16))),'Category Rules'!$E$11,IF(AND('Category Rules'!$B$12="Yes",C16<>"",ISNUMBER(SEARCH('Category Rules'!$E$12,C16))),'Category Rules'!$E$12,IF(AND('Category Rules'!$B$13="Yes",C16<>"",ISNUMBER(SEARCH('Category Rules'!$E$13,C16))),'Category Rules'!$E$13,IF(AND('Category Rules'!$B$14="Yes",C16<>"",ISNUMBER(SEARCH('Category Rules'!$E$14,C16))),'Category Rules'!$E$14,IF(AND('Category Rules'!$B$15="Yes",C16<>"",ISNUMBER(SEARCH('Category Rules'!$E$15,C16))),'Category Rules'!$E$15,IF(AND('Category Rules'!$B$16="Yes",C16<>"",ISNUMBER(SEARCH('Category Rules'!$E$16,C16))),'Category Rules'!$E$16,IF(AND('Category Rules'!$B$17="Yes",C16<>"",ISNUMBER(SEARCH('Category Rules'!$E$17,C16))),'Category Rules'!$E$17,IF(AND('Category Rules'!$B$18="Yes",C16<>"",ISNUMBER(SEARCH('Category Rules'!$E$18,C16))),'Category Rules'!$E$18,IF(AND('Category Rules'!$B$19="Yes",C16<>"",ISNUMBER(SEARCH('Category Rules'!$E$19,C16))),'Category Rules'!$E$19,"No rule matched"))))))))))))))))) | P16: =IF(OR(A16="",B16="",C16="",H16=""),"",TEXT(A16,"yyyymmdd")&"|"&B16&"|"&C16&"|"&TEXT(H16,"0.00"))
... N54: =IF('Raw Import'!K54="","",'Raw Import'!K54) | O54: =IF(C54="","",IF(AND('Category Rules'!$B$4="Yes",C54<>"",ISNUMBER(SEARCH('Category Rules'!$E$4,C54))),'Category Rules'!$E$4,IF(AND('Category Rules'!$B$5="Yes",C54<>"",ISNUMBER(SEARCH('Category Rules'!$E$5,C54))),'Category Rules'!$E$5,IF(AND('Category Rules'!$B$6="Yes",C54<>"",ISNUMBER(SEARCH('Category Rules'!$E$6,C54))),'Category Rules'!$E$6,IF(AND('Category Rules'!$B$7="Yes",C54<>"",ISNUMBER(SEARCH('Category Rules'!$E$7,C54))),'Category Rules'!$E$7,IF(AND('Category Rules'!$B$8="Yes",C54<>"",ISNUMBER(SEARCH('Category Rules'!$E$8,C54))),'Category Rules'!$E$8,IF(AND('Category Rules'!$B$9="Yes",C54<>"",ISNUMBER(SEARCH('Category Rules'!$E$9,C54))),'Category Rules'!$E$9,IF(AND('Category Rules'!$B$10="Yes",C54<>"",ISNUMBER(SEARCH('Category Rules'!$E$10,C54))),'Category Rules'!$E$10,IF(AND('Category Rules'!$B$11="Yes",C54<>"",ISNUMBER(SEARCH('Category Rules'!$E$11,C54))),'Category Rules'!$E$11,IF(AND('Category Rules'!$B$12="Yes",C54<>"",ISNUMBER(SEARCH('Category Rules'!$E$12,C54))),'Category Rules'!$E$12,IF(AND('Category Rules'!$B$13="Yes",C54<>"",ISNUMBER(SEARCH('Category Rules'!$E$13,C54))),'Category Rules'!$E$13,IF(AND('Category Rules'!$B$14="Yes",C54<>"",ISNUMBER(SEARCH('Category Rules'!$E$14,C54))),'Category Rules'!$E$14,IF(AND('Category Rules'!$B$15="Yes",C54<>"",ISNUMBER(SEARCH('Category Rules'!$E$15,C54))),'Category Rules'!$E$15,IF(AND('Category Rules'!$B$16="Yes",C54<>"",ISNUMBER(SEARCH('Category Rules'!$E$16,C54))),'Category Rules'!$E$16,IF(AND('Category Rules'!$B$17="Yes",C54<>"",ISNUMBER(SEARCH('Category Rules'!$E$17,C54))),'Category Rules'!$E$17,IF(AND('Category Rules'!$B$18="Yes",C54<>"",ISNUMBER(SEARCH('Category Rules'!$E$18,C54))),'Category Rules'!$E$18,IF(AND('Category Rules'!$B$19="Yes",C54<>"",ISNUMBER(SEARCH('Category Rules'!$E$19,C54))),'Category Rules'!$E$19,"No rule matched"))))))))))))))))) | P54: =IF(OR(A54="",B54="",C54="",H54=""),"",TEXT(A54,"yyyymmdd")&"|"&B54&"|"&C54&"|"&TEXT(H54,"0.00"))

Sheet Budget
A1: Monthly Budget & Variance
A3: Category | B3: Subcategory | C3: Budget / Month | D3: Actual / Month | E3: Variance | F3: % Used | G3: Fixed / Variable | H3: Notes
A4: Housing | B4: Rent / Mortgage | C4: 0 | D4: =SUMIFS(Transactions!$H:$H,Transactions!$E:$E,A4,Transactions!$F:$F,B4,Transactions!$D:$D,"Expense")*-1 | E4: =C4-D4 | F4: =IFERROR(D4/C4,0) | G4: Fixed
A5: Housing | B5: Utilities | C5: 0 | D5: =SUMIFS(Transactions!$H:$H,Transactions!$E:$E,A5,Transactions!$F:$F,B5,Transactions!$D:$D,"Expense")*-1 | E5: =C5-D5 | F5: =IFERROR(D5/C5,0) | G5: Variable
A6: Food | B6: Groceries | C6: 0 | D6: =SUMIFS(Transactions!$H:$H,Transactions!$E:$E,A6,Transactions!$F:$F,B6,Transactions!$D:$D,"Expense")*-1 | E6: =C6-D6 | F6: =IFERROR(D6/C6,0) | G6: Variable
A7: Food | B7: Dining Out | C7: 0 | D7: =SUMIFS(Transactions!$H:$H,Transactions!$E:$E,A7,Transactions!$F:$F,B7,Transactions!$D:$D,"Expense")*-1 | E7: =C7-D7 | F7: =IFERROR(D7/C7,0) | G7: Variable
A8: Transportation | B8: Car / Transit | C8: 0 | D8: =SUMIFS(Transactions!$H:$H,Transactions!$E:$E,A8,Transactions!$F:$F,B8,Transactions!$D:$D,"Expense")*-1 | E8: =C8-D8 | F8: =IFERROR(D8/C8,0) | G8: Variable
A9: Insurance | B9: Insurance | C9: 0 | D9: =SUMIFS(Transactions!$H:$H,Transactions!$E:$E,A9,Transactions!$F:$F,B9,Transactions!$D:$D,"Expense")*-1 | E9: =C9-D9 | F9: =IFERROR(D9/C9,0) | G9: Fixed
A10: Debt | B10: Debt Payments | C10: 0 | D10: =SUMIFS(Transactions!$H:$H,Transactions!$E:$E,A10,Transactions!$F:$F,B10,Transactions!$D:$D,"Expense")*-1 | E10: =C10-D10 | F10: =IFERROR(D10/C10,0) | G10: Fixed
A11: Subscriptions | B11: Subscriptions | C11: 0 | D11: =SUMIFS(Transactions!$H:$H,Transactions!$E:$E,A11,Transactions!$F:$F,B11,Transactions!$D:$D,"Expense")*-1 | E11: =C11-D11 | F11: =IFERROR(D11/C11,0) | G11: Fixed
A12: Personal | B12: Shopping | C12: 0 | D12: =SUMIFS(Transactions!$H:$H,Transactions!$E:$E,A12,Transactions!$F:$F,B12,Transactions!$D:$D,"Expense")*-1 | E12: =C12-D12 | F12: =IFERROR(D12/C12,0) | G12: Variable
A13: Entertainment | B13: Entertainment | C13: 0 | D13: =SUMIFS(Transactions!$H:$H,Transactions!$E:$E,A13,Transactions!$F:$F,B13,Transactions!$D:$D,"Expense")*-1 | E13: =C13-D13 | F13: =IFERROR(D13/C13,0) | G13: Variable
A14: Other | B14: Other | C14: 0 | D14: =SUMIFS(Transactions!$H:$H,Transactions!$E:$E,A14,Transactions!$F:$F,B14,Transactions!$D:$D,"Expense")*-1 | E14: =C14-D14 | F14: =IFERROR(D14/C14,0) | G14: Variable

Sheet Bills
A1: Bills & Recurring Obligations
A3: Bill | B3: Category | C3: Due Day | D3: Amount | E3: Frequency | F3: Autopay? | G3: Account ID | H3: Annual Cost | I3: Notes
A4: Rent / Mortgage | B4: Housing | C4: 1 | D4: 0 | E4: Monthly | F4: Yes | G4: A001 | H4: =D4*12
A5: Electric | B5: Utilities | C5: 15 | D5: 0 | E5: Monthly | F5: Yes | G5: A001 | H5: =D5*12
A6: Internet | B6: Utilities | C6: 20 | D6: 0 | E6: Monthly | F6: Yes | G6: A001 | H6: =D6*12
A7: Phone | B7: Utilities | C7: 25 | D7: 0 | E7: Monthly | F7: Yes | G7: A001 | H7: =D7*12

Sheet Debt
A1: Debt Schedule
A3: Debt | B3: Type | C3: Interest Rate | D3: Minimum Payment | E3: Current Balance | F3: Extra Payment | G3: Payoff Priority | H3: Estimated Monthly Interest | I3: Notes
A4: Credit Card | B4: Revolving | C4: 0 | D4: 0 | E4: 0 | F4: 0 | G4: 1 | H4: =E4*C4/12
A5: Auto Loan | B5: Installment | C5: 0 | D5: 0 | E5: 0 | F5: 0 | G5: 2 | H5: =E5*C5/12
A6: Student Loan | B6: Installment | C6: 0 | D6: 0 | E6: 0 | F6: 0 | G6: 3 | H6: =E6*C6/12

Sheet Investments
A1: Investment Portfolio
A3: Account ID | B3: Security / Asset | C3: Ticker | D3: Asset Class | E3: Quantity | F3: Price | G3: Market Value | H3: Cost Basis | I3: Unrealized Gain/(Loss)
G4: =IF(OR(E4="",F4=""),"",E4*F4) | I4: =IF(OR(G4="",H4=""),"",G4-H4)
G5: =IF(OR(E5="",F5=""),"",E5*F5) | I5: =IF(OR(G5="",H5=""),"",G5-H5)
G6: =IF(OR(E6="",F6=""),"",E6*F6) | I6: =IF(OR(G6="",H6=""),"",G6-H6)
G7: =IF(OR(E7="",F7=""),"",E7*F7) | I7: =IF(OR(G7="",H7=""),"",G7-H7)
G8: =IF(OR(E8="",F8=""),"",E8*F8) | I8: =IF(OR(G8="",H8=""),"",G8-H8)
G9: =IF(OR(E9="",F9=""),"",E9*F9) | I9: =IF(OR(G9="",H9=""),"",G9-H9)
G10: =IF(OR(E10="",F10=""),"",E10*F10) | I10: =IF(OR(G10="",H10=""),"",G10-H10)
G11: =IF(OR(E11="",F11=""),"",E11*F11) | I11: =IF(OR(G11="",H11=""),"",G11-H11)
G12: =IF(OR(E12="",F12=""),"",E12*F12) | I12: =IF(OR(G12="",H12=""),"",G12-H12)
G13: =IF(OR(E13="",F13=""),"",E13*F13) | I13: =IF(OR(G13="",H13=""),"",G13-H13)

Sheet Goals
A1: Financial Goals
A3: Goal | B3: Target Amount | C3: Current Amount | D3: Target Date | E3: Monthly Contribution | F3: Required Monthly Contribution* | G3: Priority
A4: Emergency Fund | B4: 10000 | C4: 0 | E4: 0 | F4: =IF(D4="","",IFERROR(MAX(0,(B4-C4)/MAX(1,DATEDIF(TODAY(),D4,"m"))),0)) | G4: 1
A5: Down Payment | B5: 25000 | C5: 0 | E5: 0 | F5: =IF(D5="","",IFERROR(MAX(0,(B5-C5)/MAX(1,DATEDIF(TODAY(),D5,"m"))),0)) | G5: 2
A6: Investment Goal | B6: 50000 | C6: 0 | E6: 0 | F6: =IF(D6="","",IFERROR(MAX(0,(B6-C6)/MAX(1,DATEDIF(TODAY(),D6,"m"))),0)) | G6: 3

Sheet Setup
A1: Setup, Categories & Data Dictionary
A3: Recommended Workflow
A4: 1. Enter current balances in Accounts.
A5: 2. Enter recurring bills and debt balances.
A6: 3. Import/paste bank transactions into Transactions.
A7: 4. Categorize transactions consistently.
A8: 5. Set monthly budgets.
A9: 6. Update investments and goals monthly.
A10: 7. Review Dashboard for cash flow, savings rate, debt, and net worth.
A13: Security / Data Handling
A14: Do not place online-banking credentials, full account numbers, SSNs, or API secrets in this workbook.
A15: For automation, use a secure financial-data aggregator/API and map institution data into Accounts and Transactions.

Sheet Raw Import
A1: Raw Bank / API Import Layer
A3: Paste bank CSV/API output here. This is the immutable source layer; downstream formulas read from this sheet. Never store credentials, passwords, MFA codes, or API secrets here.
A4: Raw ID | B4: Date | C4: Account ID | D4: Description | E4: Amount ($) | F4: Currency | G4: Merchant | H4: Raw Category | I4: Pending? | J4: Transaction ID | K4: Source | L4: Imported At | M4: Fingerprint | N4: Notes

Sheet Field Mapping
A1: Field Mapping — Provider → Model
A3: Provider Field | B3: Model Field | C3: Transformation | D3: Required? | E3: Example | F3: Notes
A4: transaction_id | B4: Transaction ID | C4: Direct | D4: Yes | E4: abc123 | F4: Use provider unique ID when available
A5: date | B5: Date | C5: Date | D5: Yes | E5: 2026-08-19 | F5: Posting/transaction date
A6: account_id | B6: Account ID | C6: Lookup | D6: Yes | E6: A001 | F6: Map external account to internal ID
A7: merchant_name | B7: Merchant | C7: Direct | D7: No | E7: Wawa | F7: Fallback to description
A8: name/description | B8: Description | C8: Direct | D8: Yes | E8: WAWA #1234 | F8: Original source text
A9: amount | B9: Amount ($) | C9: Direct | D9: Yes | E9: -18.42 | F9: Preserve provider sign
A10: currency | B10: Currency | C10: Direct | D10: No | E10: USD | F10: Base currency used in reporting
A11: pending | B11: Pending? | C11: Boolean | D11: No | E11: FALSE | F11: Flag pending transactions

Sheet Category Rules
A1: Automatic Categorization Rules
A3: Rule ID | B3: Active? | C3: Priority | D3: Match Type | E3: Merchant / Text Pattern | F3: Category | G3: Subcategory | H3: Type Override | I3: Recurring? | J3: Notes
A4: R001 | B4: Yes | C4: 1 | D4: Contains | E4: WAWA | F4: Food | G4: Dining Out | H4: Expense | I4: No
A5: R002 | B5: Yes | C5: 2 | D5: Contains | E5: CHICK-FIL-A | F5: Food | G5: Dining Out | H5: Expense | I5: No
A6: R003 | B6: Yes | C6: 3 | D6: Contains | E6: MCDONALD | F6: Food | G6: Dining Out | H6: Expense | I6: No
A7: R004 | B7: Yes | C7: 4 | D7: Contains | E7: TARGET | F7: Shopping | G7: General | H7: Expense | I7: No
A8: R005 | B8: Yes | C8: 5 | D8: Contains | E8: WALMART | F8: Shopping | G8: General | H8: Expense | I8: No
A9: R006 | B9: Yes | C9: 6 | D9: Contains | E9: AMAZON | F9: Shopping | G9: Online Shopping | H9: Expense | I9: No
A10: R007 | B10: Yes | C10: 7 | D10: Contains | E10: UBER | F10: Transportation | G10: Rideshare | H10: Expense | I10: No
A11: R008 | B11: Yes | C11: 8 | D11: Contains | E11: LYFT | F11: Transportation | G11: Rideshare | H11: Expense | I11: No
A12: R009 | B12: Yes | C12: 9 | D12: Contains | E12: SHELL | F12: Transportation | G12: Gas | H12: Expense | I12: No
A13: R010 | B13: Yes | C13: 10 | D13: Contains | E13: EXXON | F13: Transportation | G13: Gas | H13: Expense | I13: No
A14: R011 | B14: Yes | C14: 11 | D14: Contains | E14: NETFLIX | F14: Subscriptions | G14: Streaming | H14: Expense | I14: Yes
A15: R012 | B15: Yes | C15: 12 | D15: Contains | E15: SPOTIFY | F15: Subscriptions | G15: Music | H15: Expense | I15: Yes
... A20: R017 | B20: Yes | C20: 17 | D20: Contains | E20: RENT | F20: Housing | G20: Rent / Mortgage | H20: Expense | I20: Yes

Sheet Monthly Summary
A1: Monthly Financial Summary
A3: Month | B3: Income ($) | C3: Expenses ($) | D3: Net Cash Flow ($) | E3: Savings Rate (%) | F3: Budget ($) | G3: Budget Variance ($) | H3: Notes
A4: =TEXT(EOMONTH(TODAY(),-23),"yyyy-mm") | B4: =SUMIFS(Transactions!$H:$H,Transactions!$I:$I,A4,Transactions!$D:$D,"Income") | C4: =-SUMIFS(Transactions!$H:$H,Transactions!$I:$I,A4,Transactions!$D:$D,"Expense") | D4: =B4-C4 | E4: =IFERROR(D4/B4,0) | F4: =SUM(Budget!$C$4:$C$14) | G4: =F4-C4
A5: =TEXT(EDATE(DATEVALUE(A4&"-01"),1),"yyyy-mm") | B5: =SUMIFS(Transactions!$H:$H,Transactions!$I:$I,A5,Transactions!$D:$D,"Income") | C5: =-SUMIFS(Transactions!$H:$H,Transactions!$I:$I,A5,Transactions!$D:$D,"Expense") | D5: =B5-C5 | E5: =IFERROR(D5/B5,0) | F5: =SUM(Budget!$C$4:$C$14) | G5: =F5-C5
A6: =TEXT(EDATE(DATEVALUE(A5&"-01"),1),"yyyy-mm") | B6: =SUMIFS(Transactions!$H:$H,Transactions!$I:$I,A6,Transactions!$D:$D,"Income") | C6: =-SUMIFS(Transactions!$H:$H,Transactions!$I:$I,A6,Transactions!$D:$D,"Expense") | D6: =B6-C6 | E6: =IFERROR(D6/B6,0) | F6: =SUM(Budget!$C$4:$C$14) | G6: =F6-C6
A7: =TEXT(EDATE(DATEVALUE(A6&"-01"),1),"yyyy-mm") | B7: =SUMIFS(Transactions!$H:$H,Transactions!$I:$I,A7,Transactions!$D:$D,"Income") | C7: =-SUMIFS(Transactions!$H:$H,Transactions!$I:$I,A7,Transactions!$D:$D,"Expense") | D7: =B7-C7 | E7: =IFERROR(D7/B7,0) | F7: =SUM(Budget!$C$4:$C$14) | G7: =F7-C7
A8: =TEXT(EDATE(DATEVALUE(A7&"-01"),1),"yyyy-mm") | B8: =SUMIFS(Transactions!$H:$H,Transactions!$I:$I,A8,Transactions!$D:$D,"Income") | C8: =-SUMIFS(Transactions!$H:$H,Transactions!$I:$I,A8,Transactions!$D:$D,"Expense") | D8: =B8-C8 | E8: =IFERROR(D8/B8,0) | F8: =SUM(Budget!$C$4:$C$14) | G8: =F8-C8
A9: =TEXT(EDATE(DATEVALUE(A8&"-01"),1),"yyyy-mm") | B9: =SUMIFS(Transactions!$H:$H,Transactions!$I:$I,A9,Transactions!$D:$D,"Income") | C9: =-SUMIFS(Transactions!$H:$H,Transactions!$I:$I,A9,Transactions!$D:$D,"Expense") | D9: =B9-C9 | E9: =IFERROR(D9/B9,0) | F9: =SUM(Budget!$C$4:$C$14) | G9: =F9-C9
A10: =TEXT(EDATE(DATEVALUE(A9&"-01"),1),"yyyy-mm") | B10: =SUMIFS(Transactions!$H:$H,Transactions!$I:$I,A10,Transactions!$D:$D,"Income") | C10: =-SUMIFS(Transactions!$H:$H,Transactions!$I:$I,A10,Transactions!$D:$D,"Expense") | D10: =B10-C10 | E10: =IFERROR(D10/B10,0) | F10: =SUM(Budget!$C$4:$C$14) | G10: =F10-C10
A11: =TEXT(EDATE(DATEVALUE(A10&"-01"),1),"yyyy-mm") | B11: =SUMIFS(Transactions!$H:$H,Transactions!$I:$I,A11,Transactions!$D:$D,"Income") | C11: =-SUMIFS(Transactions!$H:$H,Transactions!$I:$I,A11,Transactions!$D:$D,"Expense") | D11: =B11-C11 | E11: =IFERROR(D11/B11,0) | F11: =SUM(Budget!$C$4:$C$14) | G11: =F11-C11
A12: =TEXT(EDATE(DATEVALUE(A11&"-01"),1),"yyyy-mm") | B12: =SUMIFS(Transactions!$H:$H,Transactions!$I:$I,A12,Transactions!$D:$D,"Income") | C12: =-SUMIFS(Transactions!$H:$H,Transactions!$I:$I,A12,Transactions!$D:$D,"Expense") | D12: =B12-C12 | E12: =IFERROR(D12/B12,0) | F12: =SUM(Budget!$C$4:$C$14) | G12: =F12-C12
A13: =TEXT(EDATE(DATEVALUE(A12&"-01"),1),"yyyy-mm") | B13: =SUMIFS(Transactions!$H:$H,Transactions!$I:$I,A13,Transactions!$D:$D,"Income") | C13: =-SUMIFS(Transactions!$H:$H,Transactions!$I:$I,A13,Transactions!$D:$D,"Expense") | D13: =B13-C13 | E13: =IFERROR(D13/B13,0) | F13: =SUM(Budget!$C$4:$C$14) | G13: =F13-C13
A14: =TEXT(EDATE(DATEVALUE(A13&"-01"),1),"yyyy-mm") | B14: =SUMIFS(Transactions!$H:$H,Transactions!$I:$I,A14,Transactions!$D:$D,"Income") | C14: =-SUMIFS(Transactions!$H:$H,Transactions!$I:$I,A14,Transactions!$D:$D,"Expense") | D14: =B14-C14 | E14: =IFERROR(D14/B14,0) | F14: =SUM(Budget!$C$4:$C$14) | G14: =F14-C14
A15: =TEXT(EDATE(DATEVALUE(A14&"-01"),1),"yyyy-mm") | B15: =SUMIFS(Transactions!$H:$H,Transactions!$I:$I,A15,Transactions!$D:$D,"Income") | C15: =-SUMIFS(Transactions!$H:$H,Transactions!$I:$I,A15,Transactions!$D:$D,"Expense") | D15: =B15-C15 | E15: =IFERROR(D15/B15,0) | F15: =SUM(Budget!$C$4:$C$14) | G15: =F15-C15
A16: =TEXT(EDATE(DATEVALUE(A15&"-01"),1),"yyyy-mm") | B16: =SUMIFS(Transactions!$H:$H,Transactions!$I:$I,A16,Transactions!$D:$D,"Income") | C16: =-SUMIFS(Transactions!$H:$H,Transactions!$I:$I,A16,Transactions!$D:$D,"Expense") | D16: =B16-C16 | E16: =IFERROR(D16/B16,0) | F16: =SUM(Budget!$C$4:$C$14) | G16: =F16-C16
... A27: =TEXT(EDATE(DATEVALUE(A26&"-01"),1),"yyyy-mm") | B27: =SUMIFS(Transactions!$H:$H,Transactions!$I:$I,A27,Transactions!$D:$D,"Income") | C27: =-SUMIFS(Transactions!$H:$H,Transactions!$I:$I,A27,Transactions!$D:$D,"Expense") | D27: =B27-C27 | E27: =IFERROR(D27/B27,0) | F27: =SUM(Budget!$C$4:$C$14) | G27: =F27-C27

Sheet Data Dictionary
A1: Data Dictionary & Integration Contract
A3: Field | B3: Layer | C3: Type | D3: Purpose | E3: Example | F3: Source | G3: Required?
A4: Account ID | B4: Accounts / Transactions | C4: Text | D4: Internal account key | E4: A001 | F4: Internal | G4: Yes
A5: Transaction ID | B5: Raw Import / Transactions | C5: Text | D5: Provider unique transaction identifier | E5: tx_123 | F5: Bank/API | G5: Yes
A6: Date | B6: Transactions | C6: Date | D6: Posting/transaction date | E6: 08/19/2026 | F6: Bank/API | G6: Yes
A7: Merchant | B7: Transactions | C7: Text | D7: Normalized merchant name | E7: Wawa | F7: Bank/API + rules | G7: No
A8: Signed Amount ($) | B8: Transactions | C8: Number | D8: Income positive; expenses negative | E8: -18.42 | F8: Bank/API | G8: Yes
A9: Type | B9: Transactions | C9: Enum | D9: Income / Expense / Transfer / Investment | E9: Expense | F9: Rules | G9: Yes
A10: Category | B10: Transactions | C10: Enum | D10: Top-level budget category | E10: Food | F10: Rules | G10: Yes
A11: Subcategory | B11: Transactions | C11: Text | D11: Detailed classification | E11: Dining Out | F11: Rules | G11: Yes
A12: Review Status | B12: Transactions | C12: Enum | D12: OK / Review | E12: Review | F12: Rules | G12: Yes

Sheet Settings
A1: Model Settings & Security
A3: Setting | B3: Value | C3: Purpose
A4: Base Currency | B4: USD | C4: Reporting currency
A5: Review Uncategorized | B5: Yes | C5: Flag transactions with no matching rule
A6: Exclude Pending | B6: Yes | C6: Recommended for finalized reporting
A7: Duplicate Key | B7: Transaction ID + Fingerprint | C7: Prevent duplicate imports
A8: Import Frequency | B8: Daily | C8: Recommended automation cadence
A11: SECURITY — Keep bank credentials, MFA codes, API secrets, access tokens, SSNs and full account numbers outside the workbook.
